Metadata-Version: 2.1
Name: awstokensave
Version: 0.1
Summary: This script is for read the env file and then search for the aws temporary credentials after that set it on ~/.aws/credentials file with profile name
Home-page: https://github.com/h4rithd/awsTokenEx
Author: h4rithd
Author-email: h4rithd@pm.me
License: MIT
Keywords: awstokenex aws aws-token aws-secret AWS_ACCESS_KEY_ID AWS_SECRET_ACCESS_KEY AWS_SESSION_TOKEN
Platform: UNKNOWN
Classifier: Development Status :: 5 - Production/Stable
Classifier: Environment :: Console
Classifier: Intended Audience :: Developers
Classifier: Intended Audience :: System Administrators
Classifier: Natural Language :: English
Classifier: Operating System :: MacOS
Classifier: Operating System :: Microsoft :: Windows
Classifier: Operating System :: POSIX
Classifier: Programming Language :: Python :: 3.9
Classifier: Programming Language :: Python :: 3.10
License-File: LICENCE.txt
